mhi/common/__init__.py
mhi/common/__main__.py
mhi/common/_monkey_patch.py
mhi/common/_script.py
mhi/common/arrow.py
mhi/common/cache.py
mhi/common/cdata.py
mhi/common/codec.py
mhi/common/collection.py
mhi/common/colour.py
mhi/common/config.py
mhi/common/help.py
mhi/common/path.py
mhi/common/platform.py
mhi/common/process.py
mhi/common/py.typed
mhi/common/remote.py
mhi/common/server.py
mhi/common/version.py
mhi/common/warnings.py
mhi/common/zipper.py
mhi_common-3.1.6.dist-info/licenses/LICENSE
mhi_common-3.1.6.dist-info/METADATA
mhi_common-3.1.6.dist-info/WHEEL
mhi_common-3.1.6.dist-info/top_level.txt
mhi_common-3.1.6.dist-info/RECORD
